outlier/OUTLIER_akashjindal347.py
outlier/__init__.py
outlier_akashjindal347-0.0.1.dist-info/LICENSE
outlier_akashjindal347-0.0.1.dist-info/METADATA
outlier_akashjindal347-0.0.1.dist-info/WHEEL
outlier_akashjindal347-0.0.1.dist-info/top_level.txt
outlier_akashjindal347-0.0.1.dist-info/RECORD
