Metadata-Version: 2.1
Name: outlier-akashjindal347
Version: 0.0.1
Summary: Outlier
Home-page: https://github.com/akashjindal347/Python-Packages
Author: Akash Jindal
Author-email: akashjindal347@gmail.com
License: UNKNOWN
Platform: UNKNOWN
Classifier: Programming Language :: Python :: 3
Classifier: License :: OSI Approved :: MIT License
Classifier: Operating System :: OS Independent
Requires-Python: >=3.6
